lux/__init__.py
lux/auto_complete.py
lux/bot.py
lux/cli.py
lux/cog.py
lux/config.py
lux/context_var.py
lux/env.py
lux/logger.py
lux/utility.py
lux_discord-0.1.0.dist-info/LICENSE
lux_discord-0.1.0.dist-info/METADATA
lux_discord-0.1.0.dist-info/WHEEL
lux_discord-0.1.0.dist-info/RECORD
